odoo/addons/hr_holidays_hour/README.rst
odoo/addons/hr_holidays_hour/__init__.py
odoo/addons/hr_holidays_hour/__manifest__.py
odoo/addons/hr_holidays_hour/i18n/de.po
odoo/addons/hr_holidays_hour/i18n/fr.po
odoo/addons/hr_holidays_hour/i18n/hr_holidays_hour.pot
odoo/addons/hr_holidays_hour/i18n/it.po
odoo/addons/hr_holidays_hour/models/__init__.py
odoo/addons/hr_holidays_hour/models/hr_employee.py
odoo/addons/hr_holidays_hour/models/hr_leave.py
odoo/addons/hr_holidays_hour/models/hr_leave_allocation.py
odoo/addons/hr_holidays_hour/readme/CONFIGURE.rst
odoo/addons/hr_holidays_hour/readme/CONTRIBUTORS.rst
odoo/addons/hr_holidays_hour/readme/DESCRIPTION.rst
odoo/addons/hr_holidays_hour/readme/INSTALL.rst
odoo/addons/hr_holidays_hour/report/__init__.py
odoo/addons/hr_holidays_hour/report/hr_leave_report.py
odoo/addons/hr_holidays_hour/report/hr_leave_report.xml
odoo/addons/hr_holidays_hour/static/description/icon.png
odoo/addons/hr_holidays_hour/static/description/index.html
odoo/addons/hr_holidays_hour/tests/__init__.py
odoo/addons/hr_holidays_hour/tests/test_hr_holidays.py
odoo/addons/hr_holidays_hour/tests/test_leave_hours.py
odoo/addons/hr_holidays_hour/views/hr_employee.xml
odoo12_addon_hr_holidays_hour-12.0.1.0.0.99.dev9.dist-info/METADATA
odoo12_addon_hr_holidays_hour-12.0.1.0.0.99.dev9.dist-info/WHEEL
odoo12_addon_hr_holidays_hour-12.0.1.0.0.99.dev9.dist-info/top_level.txt
odoo12_addon_hr_holidays_hour-12.0.1.0.0.99.dev9.dist-info/RECORD
